CHANGES.txt
CONTRIBUTORS.txt
MANIFEST.in
README.txt
setup.cfg
setup.py
src/drchitu/__init__.py
src/drchitu.XMLTransformer.egg-info/PKG-INFO
src/drchitu.XMLTransformer.egg-info/SOURCES.txt
src/drchitu.XMLTransformer.egg-info/dependency_links.txt
src/drchitu.XMLTransformer.egg-info/entry_points.txt
src/drchitu.XMLTransformer.egg-info/namespace_packages.txt
src/drchitu.XMLTransformer.egg-info/not-zip-safe
src/drchitu.XMLTransformer.egg-info/paster_plugins.txt
src/drchitu.XMLTransformer.egg-info/requires.txt
src/drchitu.XMLTransformer.egg-info/top_level.txt
src/drchitu/XMLTransformer/README.txt
src/drchitu/XMLTransformer/__init__.py
src/drchitu/XMLTransformer/config.py
src/drchitu/XMLTransformer/configure.zcml
src/drchitu/XMLTransformer/testing.py
src/drchitu/XMLTransformer/browser/__init__.py
src/drchitu/XMLTransformer/browser/configure.zcml
src/drchitu/XMLTransformer/browser/xmltransformer.pt
src/drchitu/XMLTransformer/browser/xmltransformer_license.pt
src/drchitu/XMLTransformer/browser/xmltransformer_view.py
src/drchitu/XMLTransformer/content/__init__.py
src/drchitu/XMLTransformer/content/configure.zcml
src/drchitu/XMLTransformer/content/xmltransformertype.py
src/drchitu/XMLTransformer/interfaces/__init__.py
src/drchitu/XMLTransformer/interfaces/xmltransformertype.py
src/drchitu/XMLTransformer/portlets/__init__.py
src/drchitu/XMLTransformer/portlets/configure.zcml
src/drchitu/XMLTransformer/profiles/default/factorytool.xml
src/drchitu/XMLTransformer/profiles/default/metadata.xml
src/drchitu/XMLTransformer/profiles/default/portlets.xml
src/drchitu/XMLTransformer/profiles/default/rolemap.xml
src/drchitu/XMLTransformer/profiles/default/types.xml
src/drchitu/XMLTransformer/profiles/default/types/XMLTransformer_Type.xml
src/drchitu/XMLTransformer/tests/__init__.py
src/drchitu/XMLTransformer/tests/base.py
src/drchitu/XMLTransformer/tests/test_doctest.py
src/drchitu/XMLTransformer/tests/test_example.py
src/drchitu/XMLTransformer/tests/test_robot.py