Metadata-Version: 1.1
Name: drchitu.XMLTransformer
Version: 1.2
Summary: Transforms XML into HTML using XSLT.
Home-page: http://svn.plone.org/svn/collective/
Author: Dr. Christoph Hermann
Author-email: info@drhermann.de
License: gpl
Keywords: XML,XSLT,HTML,Transformation
Platform: UNKNOWN
Classifier: Framework :: Plone
Classifier: Intended Audience :: Developers
